notebooks/sat6_cnn/T1-8bit/build_t1w8_v3/stitched_ip/finn_design.v
// Copyright 1986-2022 Xilinx, Inc. All Rights Reserved.
// Copyright 2022-2023 Advanced Micro Devices, Inc. All Rights Reserved.
// --------------------------------------------------------------------------------
// Tool Version: Vivado v.2023.2 (lin64) Build 4029153 Fri Oct 13 20:13:54 MDT 2023
// Date        : Tue Mar 12 05:14:09 2024
// Host        : finn_dev_artti running 64-bit Ubuntu 22.04.1 LTS
// Command     : write_verilog -force -mode synth_stub finn_design.v
// Design      : finn_design_wrapper
// Purpose     : Stub declaration of top-level module interface
// Device      : xc7z020clg484-1
// --------------------------------------------------------------------------------

// This empty module with port declaration file causes synthesis tools to infer a black box for IP.
// The synthesis directives are for Synopsys Synplify support to prevent IO buffer insertion.
// Please paste the declaration into a Verilog source file or add the file as an additional source.
module finn_design_wrapper(ap_clk, ap_rst_n, m_axis_0_tdata, 
  m_axis_0_tready, m_axis_0_tvalid, s_axis_0_tdata, s_axis_0_tready, s_axis_0_tvalid)
/* synthesis syn_black_box black_box_pad_pin="ap_rst_n,m_axis_0_tdata[7:0],m_axis_0_tready,m_axis_0_tvalid,s_axis_0_tdata[7:0],s_axis_0_tready,s_axis_0_tvalid" */
/* synthesis syn_force_seq_prim="ap_clk" */;
  input ap_clk /* synthesis syn_isclock = 1 */;
  input ap_rst_n;
  output [7:0]m_axis_0_tdata;
  input m_axis_0_tready;
  output m_axis_0_tvalid;
  input [7:0]s_axis_0_tdata;
  output s_axis_0_tready;
  input s_axis_0_tvalid;
endmodule

notebooks/sat6_cnn/T1-8bit/build_t1w8_v3/report/verify_rtlsim_52.vcd
$version Generated by VerilatedVcd $end
$date Tue Mar 12 05:21:17 2024 $end
$timescale 1ps $end

 $scope module TOP $end
  $var wire  1 # ap_clk $end
  $var wire  1 $ ap_rst_n $end
  $var wire  8 % m_axis_0_tdata [7:0] $end
  $var wire  1 & m_axis_0_tready $end
  $var wire  1 ' m_axis_0_tvalid $end
  $var wire  8 ( s_axis_0_tdata [7:0] $end
  $var wire  1 ) s_axis_0_tready $end
  $var wire  1 * s_axis_0_tvalid $end
  $scope module finn_design_wrapper $end
   $var wire  1 # ap_clk $end
   $var wire  1 $ ap_rst_n $end
   $var wire  8 % m_axis_0_tdata [7:0] $end
   $var wire  1 & m_axis_0_tready $end
   $var wire  1 ' m_axis_0_tvalid $end
   $var wire  8 ( s_axis_0_tdata [7:0] $end
   $var wire  1 ) s_axis_0_tready $end
   $var wire  1 * s_axis_0_tvalid $end
  $upscope $end
 $upscope $end
$enddefinitions $end


#5
1#
1$
b00000000 %
0&
0'
b00000000 (
1)
0*
#10
#15
#20
#25
1&
b10000111 (
1*
#30
#35
0#
b10001010 (
#40
#45
1#
#50
#55
0#
b10000010 (
#60
#65
1#
#70
#75
0#
b10110111 (
#80
#85
1#
#90
#95
0#
b01110100 (
#100
#105
1#
#110
#115
0#
#120
#125
1#
#130
#135
0#
b01101100 (
#140
#145
1#
#150
#155
0#
b10101001 (
#160
#165
1#
#170
#175
0#
b00101110 (
#180
#185
1#
#190
#195
0#
b00100010 (
#200
#205
1#
#210
#215
0#
b00010110 (
#220
#225
1#
#230
#235
0#
b00110001 (
#240
#245
1#
#250
#255
0#
b00111101 (
#260
#265
1#
#270
#275
0#
b00110010 (
#280
#285
1#
#290
#295
0#
b00101110 (
#300
#305
1#
#310
#315
0#
b01010011 (
#320
#325
1#
#330
#335
0#
b01000111 (
#340
#345
1#
#350
#355
0#
b00111111 (
#360
#365
1#
#370
#375
0#
#380
#385
1#
#390
#395
0#
b01100001 (
#400
#405
1#
#410
#415
0#
b01001000 (
#420
#425
1#
#430
#435
0#
b01000110 (
#440
#445
1#
#450
#455
0#
b01001000 (
#460
#465
1#
#470
#475
0#
b01011001 (
#480
#485
1#
#490
#495
0#
b00111010 (
#500
#505
1#
#510
#515
0#
b00110111 (
#520
#525
1#
#530
#535
0#
b00110110 (
#540
#545
1#
#550
#555
0#
b01001001 (
#560
#565
1#
#570
#575
0#
b01000000 (
#580
#585
1#
#590
#595
0#
b00111001 (
#600
#605
1#
#610
#615
0#
b00110110 (
#620
#625
1#
#630
#635
0#
b01001111 (
#640
#645
1#
#650
#655
0#
b01111111 (
#660
#665
1#
#670
#675
0#
b10000101 (
#680
#685
1#
#690
#695
0#
b10010000 (
#700
#705
1#
#710
#715
0#
b10101111 (
#720
#725
1#
#730
#735
0#
b10001010 (
#740
#745
1#
#750
#755
0#
b10010001 (
#760
#765
1#
#770
#775
0#
b10010110 (
#780
#785
1#
#790
#795
0#
b10110101 (
#800
#805
1#
#810
#815
0#
b01111001 (
#820
#825
1#
#830
#835
0#
b10000001 (
#840
#845
1#
#850
#855
0#
b01111010 (
#860
#865
1#
#870
#875
0#
b10101110 (
#880
#885
1#
#890
#895
0#
b01010001 (
#900
#905
1#
#910
#915
0#
b01001111 (
#920
#925
1#
#930
#935
0#
b00111111 (
#940
#945
1#
#950
#955
0#
b10001010 (
#960
#965
1#
#970
#975
0#
b01011000 (
#980
#985
1#
#990
#995
0#
b01010101 (
#1000
#1005
1#
#1010
#1015
0#
b01000011 (
#1020
#1025
1#
#1030
#1035
0#
b10010001 (
#1040
#1045
1#
#1050
#1055
0#
b10000001 (
#1060
#1065
1#
#1070
#1075
0#
b10001010 (
#1080
#1085
1#
#1090
#1095
0#
b01111101 (
#1100
#1105
1#
#1110
#1115
0#
b10110111 (
#1120
#1125
1#
#1130
#1135
0#
b01111011 (
#1140
#1145
1#
#1150
#1155
0#
b01111101 (
#1160
#1165
1#
#1170
#1175
0#
b01110100 (
#1180
#1185
1#
#1190
#1195
0#
b10110001 (
#1200
#1205
1#
#1210
#1215
0#
b10000101 (
#1220
#1225
1#
#1230
#1235
0#
b10001100 (
#1240
#1245
1#
#1250
#1255
0#
b10000011 (
#1260
#1265
1#
#1270
#1275
0#
b10110011 (
#1280
#1285
1#
#1290
#1295
0#
b10001010 (
#1300
#1305
1#
#1310
#1315
0#
b10010000 (
#1320
#1325
1#
#1330
#1335
0#
b10001110 (
#1340
#1345
1#
#1350
#1355
0#
b10111001 (
#1360
#1365
1#
#1370
#1375
0#
b01111101 (
#1380
#1385
1#
#1390
#1395
0#
b01111111 (
#1400
#1405
1#
#1410
#1415
0#
b01111101 (
#1420
#1425
1#
#1430
#1435
0#
b10110000 (
#1440
#1445
1#
#1450
#1455
0#
b01011111 (
#1460
#1465
1#
#1470
#1475
0#
b01011001 (
#1480
#1485
1#
#1490
#1495
0#
b01001111 (
#1500
#1505
1#
#1510
#1515
0#
b10001001 (
#1520
#1525
1#
#1530
#1535
0#
b00110111 (
#1540
#1545
1#
#1550
#1555
0#
b00101111 (
#1560
#1565
1#
#1570
#1575
0#
b00011111 (
#1580
#1585
1#
#1590
#1595
0#
b01010101 (
#1600
#1605
1#
#1610
#1615
0#
b10000010 (
#1620
#1625
1#
#1630
#1635
0#
b10000001 (
#1640
#1645
1#
#1650
#1655
0#
b01111010 (
#1660
#1665
1#
#1670
#1675
0#
b10110011 (
#1680
#1685
1#
#1690
#1695
0#
b10000110 (
#1700
#1705
1#
#1710
#1715
0#
b10000101 (
#1720
#1725
1#
#1730
#1735
0#
b10000010 (
#1740
#1745
1#
#1750
#1755
0#
b10110011 (
#1760
#1765
1#
#1770
#1775
0#
b10000101 (
#1780
#1785
1#
#1790
#1795
0#
b10000110 (
#1800
#1805
1#
#1810
#1815
0#
b10000010 (
#1820
#1825
1#
#1830
#1835
0#
b10110010 (
#1840
#1845
1#
#1850
#1855
0#
b10000100 (
#1860
#1865
1#
#1870
#1875
0#
b10001101 (
#1880
#1885
1#
#1890
#1895
0#
b10000100 (
#1900
#1905
1#
#1910
#1915
0#
b10110100 (
#1920
#1925
1#
#1930
#1935
0#
b10000001 (
#1940
#1945
1#
#1950
#1955
0#
b10000110 (
#1960
#1965
1#
#1970
#1975
0#
b01111101 (
#1980
#1985
1#
#1990
#1995
0#
b10110001 (
#2000
#2005
1#
#2010
#2015
0#
b10001000 (
#2020
#2025
1#
#2030
#2035
0#
b10001101 (
#2040
#2045
1#
#2050
#2055
0#
b10001001 (
#2060
#2065
1#
#2070
#2075
0#
b10110001 (
#2080
#2085
1#
#2090
#2095
0#
b01011010 (
#2100
#2105
1#
#2110
#2115
0#
b01010111 (
#2120
#2125
1#
#2130
#2135
0#
b01001001 (
#2140
#2145
1#
#2150
#2155
0#
b10000001 (
#2160
#2165
1#
#2170
#2175
0#
b01001001 (
#2180
#2185
1#
#2190
#2195
0#
b01000010 (
#2200
#2205
1#
#2210
#2215
0#
b00110111 (
#2220
#2225
1#
#2230
#2235
0#
b01101100 (
#2240
#2245
1#
#2250
#2255
0#
b00000000 (
